{"ProjectBreakpoints":"{\"Value\":{},\"CodeBreakpoints\":{}}","Compiler":"2","ProjectWatches":"{\"Value\":[]}","OpenedDocuments":"[{\"DocumentPath\":\"Main.xaml\",\"FactoryId\":\"{ACB8E7BA-F093-44C1-9B50-33ECA51AAE16}\"},{\"DocumentPath\":\"IMDB/IMDB-OpenIIMDBandSearch.xaml\",\"FactoryId\":\"{ACB8E7BA-F093-44C1-9B50-33ECA51AAE16}\"},{\"DocumentPath\":\"IMDB/IMDB-GetMovieName.xaml\",\"FactoryId\":\"{ACB8E7BA-F093-44C1-9B50-33ECA51AAE16}\"}]","ProjectActivitiesViewState":"{\"IMDB/IMDB-WriteToNotbad.xaml\":[],\"Main.xaml\":[{\"ActivityIdRef\":\"InvokeWorkflowFile_1\",\"IsAdvancedOptionsExpanded\":false,\"Categories\":{\"Common\":true,\"Options\":true,\"Log\":true,\"Output\":true},\"Widgets\":{}},{\"ActivityIdRef\":\"InvokeWorkflowFile_2\",\"IsAdvancedOptionsExpanded\":false,\"Categories\":{\"Common\":true,\"Options\":true,\"Log\":true},\"Widgets\":{}},{\"ActivityIdRef\":\"InvokeWorkflowFile_3\",\"IsAdvancedOptionsExpanded\":false,\"Categories\":{\"Common\":true,\"Options\":true,\"Log\":true,\"Output\":true},\"Widgets\":{}},{\"ActivityIdRef\":\"InvokeWorkflowFile_4\",\"IsAdvancedOptionsExpanded\":false,\"Categories\":{\"Common\":true,\"Options\":true,\"Log\":true,\"Output\":true},\"Widgets\":{}},{\"ActivityIdRef\":\"InvokeWorkflowFile_6\",\"IsAdvancedOptionsExpanded\":false,\"Categories\":{\"Common\":true,\"Options\":true,\"Log\":true},\"Widgets\":{}},{\"ActivityIdRef\":\"InvokeWorkflowFile_5\",\"IsAdvancedOptionsExpanded\":false,\"Categories\":{\"Common\":true,\"Options\":true,\"Log\":true,\"Output\":true},\"Widgets\":{}},{\"ActivityIdRef\":\"InterruptibleDoWhile_1\",\"IsAdvancedOptionsExpanded\":false,\"Categories\":{\"\":true},\"Widgets\":{\"Body\":{\"ShowExpanded\":true}}}],\"IMDB/IMDB-OpenIIMDBandSearch.xaml\":[{\"ActivityIdRef\":\"Delay_1\",\"IsAdvancedOptionsExpanded\":false,\"Widgets\":{\"Duration\":{\"ShowExpressionEditor\":true}}}],\"IMDB/IMDB-GetMovieName.xaml\":[{\"ActivityIdRef\":\"LogMessage_1\",\"IsAdvancedOptionsExpanded\":false,\"Widgets\":{}},{\"ActivityIdRef\":\"LogMessage_2\",\"IsAdvancedOptionsExpanded\":false,\"Widgets\":{}}],\"Main Flowchart.xaml\":[{\"ActivityIdRef\":\"InvokeWorkflowFile_5\",\"IsAdvancedOptionsExpanded\":false,\"Categories\":{\"Common\":true,\"Options\":true,\"Log\":true,\"Output\":true},\"Widgets\":{}},{\"ActivityIdRef\":\"InvokeWorkflowFile_6\",\"IsAdvancedOptionsExpanded\":false,\"Categories\":{\"Common\":true,\"Options\":true,\"Log\":true},\"Widgets\":{}},{\"ActivityIdRef\":\"InvokeWorkflowFile_7\",\"IsAdvancedOptionsExpanded\":false,\"Categories\":{\"Common\":true,\"Options\":true,\"Log\":true,\"Output\":true},\"Widgets\":{}},{\"ActivityIdRef\":\"InvokeWorkflowFile_8\",\"IsAdvancedOptionsExpanded\":false,\"Categories\":{\"Common\":true,\"Options\":true,\"Log\":true},\"Widgets\":{}}],\"IMDB/IMDB-ExtractMovieData.xaml\":[]}"}